setup.cfg
setup.py
CamelToUnderline/__init__.py
CamelToUnderline/util.py
c2u.egg-info/PKG-INFO
c2u.egg-info/SOURCES.txt
c2u.egg-info/dependency_links.txt
c2u.egg-info/top_level.txt