Metadata-Version: 1.0
Name: c2u
Version: 1.21
Summary: An feature extraction algorithm
Home-page: https://github.com/zhangbo2008/CamelToUnderline
Author: zhangbo
Author-email: 15122306087@163.com
License: MIT Licence
Keywords: pip,CamelToUnderline
Platform: any
